{
  "metadata": {
    "version": "1.0",
    "last_updated": "2025-01-09",
    "source_game_version": "9.2.2025",
    "data_type": "relic",
    "file_format": "json"
  },
  "name": "T:IX Fusion",
  "description": "Increase tower health by 5%",
  "category": "Milestone Relics",
  "type": "relic",
  "focus": "utility",
  "semantic_tags": {
    "primary_function": "defensive",
    "effect_category": "survival",
    "target_type": "tower",
    "activation": "automatic",
    "damage_type": "health_reduction",
    "scaling_type": "multiplicative",
    "synergy_groups": [
      "defense",
      "health_regen"
    ],
    "optimal_use": [
      "mid_game",
      "late_game"
    ],
    "counter_enemies": [
      "all_enemies"
    ]
  },
  "notes": "Epic milestone relic, significant health improvement",
  "tier": 9,
  "unlock_method": "Milestone",
  "bonus_type": "tower_health",
  "bonus_value": 5,
  "unlock_requirement": "Milestone: Beat wave 4500 in tier 9",
  "rarity": "Epic",
  "effect": "Tower health +5%"
}